certs/__init__.py
certs/attribute.py
certs-0.1a1.dist-info/LICENSE
certs-0.1a1.dist-info/METADATA
certs-0.1a1.dist-info/WHEEL
certs-0.1a1.dist-info/top_level.txt
certs-0.1a1.dist-info/zip-safe
certs-0.1a1.dist-info/RECORD
